djseong_bar/__init__.py
djseong_bar-0.1.1.dist-info/METADATA
djseong_bar-0.1.1.dist-info/WHEEL
djseong_bar-0.1.1.dist-info/top_level.txt
djseong_bar-0.1.1.dist-info/RECORD
