Metadata-Version: 2.1
Name: djseong-bar
Version: 0.1.1
Summary: test bar
Author-email: djseong <feedback@gmail.com>
Classifier: Programming Language :: Python :: 3
Requires-Python: >=3.7
Requires-Dist: djseong-test-foo ==0.2.0
